baby/__init__.py
baby/augmentation.py
baby/brain.py
baby/brain_util.py
baby/crawler.py
baby/errors.py
baby/generator.py
baby/io.py
baby/layers.py
baby/losses.py
baby/models.py
baby/modelsets.py
baby/morph_thresh_seg.py
baby/performance.py
baby/postprocessing.py
baby/preprocessing.py
baby/profile.py
baby/segmentation.py
baby/server.py
baby/speed_tests.py
baby/utils.py
baby/visualise.py
baby/volume.py
baby/tracker/benchmark.py
baby/tracker/core.py
baby/tracker/training.py
baby/tracker/utils.py
baby/training/__init__.py
baby/training/bud_trainer.py
baby/training/cnn_trainer.py
baby/training/flattener_trainer.py
baby/training/hyper_parameter_trainer.py
baby/training/hypermodels.py
baby/training/segmentation_trainer.py
baby/training/smoothing_model_trainer.py
baby/training/training.py
baby/training/utils.py
baby/training/v1_hyper_parameter_trainer.py
baby_seg-0.30.8.dist-info/METADATA
baby_seg-0.30.8.dist-info/WHEEL
baby_seg-0.30.8.dist-info/entry_points.txt
baby_seg-0.30.8.dist-info/licenses/AUTHORS.txt
baby_seg-0.30.8.dist-info/licenses/LICENSE.txt
baby_seg-0.30.8.dist-info/RECORD
