Metadata-Version: 2.3
Name: baby-seg
Version: 0.30.8
Summary: Birth Annotator for Budding Yeast
Project-URL: Homepage, https://github.com/julianpietsch/baby
Author-email: Julian Pietsch <julian.pietsch@synmikro.mpi-marburg.mpg.de>
Classifier: Intended Audience :: Science/Research
Classifier: License :: OSI Approved :: MIT License
Classifier: Operating System :: OS Independent
Classifier: Programming Language :: Python :: 3
Classifier: Topic :: Scientific/Engineering :: Artificial Intelligence
Classifier: Topic :: Scientific/Engineering :: Image Processing
Requires-Python: >=3.6
Requires-Dist: aiohttp
Requires-Dist: imageio
Requires-Dist: matplotlib
Requires-Dist: numpy<2
Requires-Dist: pandas
Requires-Dist: pillow
Requires-Dist: requests
Requires-Dist: scikit-image
Requires-Dist: scikit-learn
Requires-Dist: scipy
Requires-Dist: tensorflow-metal; platform_system == 'Darwin' and platform_machine == 'arm64'
Requires-Dist: tensorflow<=2.14,>=1.14
Requires-Dist: tqdm
Provides-Extra: all
Requires-Dist: gaussianprocessderivatives; extra == 'all'
Provides-Extra: dev
Requires-Dist: elasticdeform; extra == 'dev'
Requires-Dist: gaussianprocessderivatives; extra == 'dev'
Requires-Dist: keras-tuner; extra == 'dev'
Requires-Dist: pytest; extra == 'dev'
